CHANGELOG.md
MANIFEST.in
README.md
pywildcard.py
setup.py
pywildcard.egg-info/PKG-INFO
pywildcard.egg-info/SOURCES.txt
pywildcard.egg-info/dependency_links.txt
pywildcard.egg-info/top_level.txt