Metadata-Version: 1.1
Name: pywildcard
Version: 1.0.10
Summary: A fork of fnmatch to implement **
Home-page: https://github.com/agalera/python-wildcard
Author: Firecarrot
Author-email: galerajimenez@gmail.com
License: GPLv3
Keywords: wildcard,pywildcard
Platform: UNKNOWN
Classifier: Development Status :: 4 - Beta
Classifier: Topic :: Software Development :: Libraries :: Python Modules
Classifier: Intended Audience :: Developers
Classifier: License :: OSI Approved :: GNU General Public License v3 (GPLv3)
Classifier: Natural Language :: English
Classifier: Programming Language :: Python :: 2
Classifier: Programming Language :: Python :: 2.6
Classifier: Programming Language :: Python :: 2.7
Classifier: Programming Language :: Python :: 3
Classifier: Programming Language :: Python :: 3.3
Classifier: Programming Language :: Python :: 3.4
Classifier: Programming Language :: Python :: 3.5
